Metadata-Version: 2.1
Name: stupidity
Version: 0.0.1
Summary: Collection of stupid python modules
Home-page: https://github.com/koirikivi/stupidity.git
Author: Rainer Koirikivi
Author-email: rainer@koirikivi.fi
License: UNKNOWN
Keywords: stupid,stupidity,idiocy
Platform: UNKNOWN
Classifier: Development Status :: 3 - Alpha
Classifier: Intended Audience :: Developers
Classifier: License :: OSI Approved :: MIT License
Classifier: Programming Language :: Python :: 3
Classifier: Programming Language :: Python :: 3.6
Classifier: Programming Language :: Python :: 3.7
Classifier: Programming Language :: Python :: 3.8
Provides-Extra: testing
